naver/__init__.py
naver/_version.py
naver/agent/__init__.py
naver/agent/automaton.py
naver/agent/smb.py
naver/agent/states.py
naver/agent/answering/__init__.py
naver/agent/answering/answerer.py
naver/agent/logic_generation/__init__.py
naver/agent/logic_generation/logic_generator.py
naver/agent/logic_generation/relation_recognizer.py
naver/agent/logic_reasoning/__init__.py
naver/agent/logic_reasoning/logic_reasoner.py
naver/agent/logic_reasoning/problog2scallop.py
naver/agent/perception/__init__.py
naver/agent/perception/captioner.py
naver/agent/perception/entity_category_extractor.py
naver/agent/perception/entity_detector.py
naver/agent/perception/perceptioner.py
naver/context/__init__.py
naver/context/attribute.py
naver/context/context.py
naver/context/entity.py
naver/context/relation.py
naver/logic/__init__.py
naver/logic/_base.py
naver/logic/problog.py
naver/logic/scallop.py
naver/tool/__init__.py
naver/tool/depth_anything.py
naver/tool/florence.py
naver/tool/internvl.py
naver/tool/sam.py
naver-0.0.2.dist-info/LICENSE
naver-0.0.2.dist-info/METADATA
naver-0.0.2.dist-info/WHEEL
naver-0.0.2.dist-info/top_level.txt
naver-0.0.2.dist-info/RECORD
