Metadata-Version: 2.1
Name: naver
Version: 0.0.2
Summary: Official implementation of NAVER.
Home-page: https://github.com/ControlNet/NAVER
Author: ControlNet
Author-email: smczx@hotmail.com
Project-URL: Bug Tracker, https://github.com/ControlNet/NAVER/issues
Project-URL: Repository, https://github.com/ControlNet/NAVER
Keywords: deep learning,pytorch,AI
Classifier: License :: OSI Approved :: Apache Software License
Classifier: Operating System :: OS Independent
Classifier: Intended Audience :: Developers
Classifier: Topic :: Scientific/Engineering :: Artificial Intelligence
Classifier: Programming Language :: Python :: 3
Classifier: Programming Language :: Python :: 3.10
Classifier: Programming Language :: Python :: 3.11
Classifier: Programming Language :: Python :: 3.12
Classifier: Programming Language :: Python :: 3.13
Requires-Python: >=3.10
License-File: LICENSE
Requires-Dist: torch
Requires-Dist: transformers
Requires-Dist: datasets
Requires-Dist: tokenizers
Requires-Dist: python-dotenv
Requires-Dist: word2number
Requires-Dist: rich
Requires-Dist: openai
Requires-Dist: scipy
Requires-Dist: accelerate
Requires-Dist: sentencepiece
Requires-Dist: orjson
Requires-Dist: bbox-visualizer
Requires-Dist: pyyaml
Requires-Dist: ollama
Requires-Dist: problog
Requires-Dist: timm
Requires-Dist: tensorneko==0.3.21
Requires-Dist: hydra-vl4ai==0.0.6
